neal/__init__.py
neal/package_info.py
neal/sampler.py
neal/simulated_annealing.py
dwave_neal-0.6.0.dist-info/LICENSE
dwave_neal-0.6.0.dist-info/METADATA
dwave_neal-0.6.0.dist-info/WHEEL
dwave_neal-0.6.0.dist-info/top_level.txt
dwave_neal-0.6.0.dist-info/RECORD
