Metadata-Version: 2.1
Name: dwave-neal
Version: 0.6.0
Summary: General Ising graph simulated annealing solver
Home-page: https://github.com/dwavesystems/dwave-neal
Author: D-Wave Systems Inc.
Author-email: wbernoudy@dwavesys.com
License: Apache 2.0
Classifier: License :: OSI Approved :: Apache Software License
Classifier: Operating System :: OS Independent
Classifier: Programming Language :: Python :: 3
Classifier: Programming Language :: Python :: 3.7
Classifier: Programming Language :: Python :: 3.8
Classifier: Programming Language :: Python :: 3.9
Classifier: Programming Language :: Python :: 3.10
Classifier: Programming Language :: Python :: 3.11
Requires-Python: >=3.7
License-File: LICENSE
